Workbook
Name MonthlyChart_Data1: OFFSET('Planned Expenses'!$C$34,0,0,1,MonthsWithActual)
Name MonthsWithActual: COUNTIF('Actual Expenses'!$C$34:$N$34,"<>"&0)

Sheet Planned Expenses
B1: PLANNED EXPENSES
C3: January | D3: February | E3: March | F3: April | G3: May | H3: June | I3: July | J3: August | K3: September | L3: October | M3: November | N3: December | O3: Total
B4: EMPLOYEE COSTS | C4: =SUM(INDIRECT("Plan_EmployeeCosts["&C$3&"]")) -> 107950 | D4: =SUM(INDIRECT("Plan_EmployeeCosts["&D$3&"]")) -> 107950 | E4: =SUM(INDIRECT("Plan_EmployeeCosts["&E$3&"]")) -> 107950 | F4: =SUM(INDIRECT("Plan_EmployeeCosts["&F$3&"]")) -> 111125 | G4: =SUM(INDIRECT("Plan_EmployeeCosts["&G$3&"]")) -> 111125 | H4: =SUM(INDIRECT("Plan_EmployeeCosts["&H$3&"]")) -> 111125 | I4: =SUM(INDIRECT("Plan_EmployeeCosts["&I$3&"]")) -> 111125 | J4: =SUM(INDIRECT("Plan_EmployeeCosts["&J$3&"]")) -> 117348 | ... O4: =SUM(INDIRECT("Plan_EmployeeCosts["&O$3&"]")) -> 1355090
B5: EMPLOYEE COSTS | C5: JANUARY | D5: FEBRUARY | E5: MARCH | F5: APRIL | G5: MAY | H5: JUNE | I5: JULY | J5: AUGUST | K5: SEPTEMBER | L5: OCTOBER | M5: NOVEMBER | N5: DECEMBER | O5: TOTAL
B6: Wages | C6: 85000 | D6: 85000 | E6: 85000 | F6: 87500 | G6: 87500 | H6: 87500 | I6: 87500 | J6: 92400 | K6: 92400 | L6: 92400 | M6: 92400 | N6: 92400 | O6: =SUM(Plan_EmployeeCosts[[#This Row],[JANUARY]:[DECEMBER]]) -> 1067000
B7: Benefits | C7: 22950 | D7: 22950 | E7: 22950 | F7: 23625 | G7: 23625 | H7: 23625 | I7: 23625 | J7: 24948 | K7: 24948 | L7: 24948 | M7: 24948 | N7: 24948 | O7: =SUM(Plan_EmployeeCosts[[#This Row],[JANUARY]:[DECEMBER]]) -> 288090
B9: OFFICE COSTS | C9: =SUM(INDIRECT("Plan_OfficeCosts["&C$3&"]")) -> 11370 | D9: =SUM(INDIRECT("Plan_OfficeCosts["&D$3&"]")) -> 11770 | E9: =SUM(INDIRECT("Plan_OfficeCosts["&E$3&"]")) -> 11770 | F9: =SUM(INDIRECT("Plan_OfficeCosts["&F$3&"]")) -> 11470 | G9: =SUM(INDIRECT("Plan_OfficeCosts["&G$3&"]")) -> 11470 | H9: =SUM(INDIRECT("Plan_OfficeCosts["&H$3&"]")) -> 11470 | I9: =SUM(INDIRECT("Plan_OfficeCosts["&I$3&"]")) -> 11470 | J9: =SUM(INDIRECT("Plan_OfficeCosts["&J$3&"]")) -> 11470 | ... O9: =SUM(INDIRECT("Plan_OfficeCosts["&O$3&"]")) -> 138740
B10: OFFICE COSTS | C10: JANUARY | D10: FEBRUARY | E10: MARCH | F10: APRIL | G10: MAY | H10: JUNE | I10: JULY | J10: AUGUST | K10: SEPTEMBER | L10: OCTOBER | M10: NOVEMBER | N10: DECEMBER | O10: TOTAL
B11: Office lease | C11: 9800 | D11: 9800 | E11: 9800 | F11: 9800 | G11: 9800 | H11: 9800 | I11: 9800 | J11: 9800 | K11: 9800 | L11: 9800 | M11: 9800 | N11: 9800 | O11: =SUM(Plan_OfficeCosts[[#This Row],[JANUARY]:[DECEMBER]]) -> 117600
B12: Gas | C12: 0 | D12: 400 | E12: 400 | F12: 100 | G12: 100 | H12: 100 | I12: 100 | J12: 100 | K12: 100 | L12: 100 | M12: 400 | N12: 400 | O12: =SUM(Plan_OfficeCosts[[#This Row],[JANUARY]:[DECEMBER]]) -> 2300
B13: Electric | C13: 300 | D13: 300 | E13: 300 | F13: 300 | G13: 300 | H13: 300 | I13: 300 | J13: 300 | K13: 300 | L13: 300 | M13: 300 | N13: 300 | O13: =SUM(Plan_OfficeCosts[[#This Row],[JANUARY]:[DECEMBER]]) -> 3600
B14: Water | C14: 40 | D14: 40 | E14: 40 | F14: 40 | G14: 40 | H14: 40 | I14: 40 | J14: 40 | K14: 40 | L14: 40 | M14: 40 | N14: 40 | O14: =SUM(Plan_OfficeCosts[[#This Row],[JANUARY]:[DECEMBER]]) -> 480
B15: Telephone | C15: 250 | D15: 250 | E15: 250 | F15: 250 | G15: 250 | H15: 250 | I15: 250 | J15: 250 | K15: 250 | L15: 250 | M15: 250 | N15: 250 | O15: =SUM(Plan_OfficeCosts[[#This Row],[JANUARY]:[DECEMBER]]) -> 3000
B16: Internet access | C16: 180 | D16: 180 | E16: 180 | F16: 180 | G16: 180 | H16: 180 | I16: 180 | J16: 180 | K16: 180 | L16: 180 | M16: 180 | N16: 180 | O16: =SUM(Plan_OfficeCosts[[#This Row],[JANUARY]:[DECEMBER]]) -> 2160
B17: Office supplies | C17: 200 | D17: 200 | E17: 200 | F17: 200 | G17: 200 | H17: 200 | I17: 200 | J17: 200 | K17: 200 | L17: 200 | M17: 200 | N17: 200 | O17: =SUM(Plan_OfficeCosts[[#This Row],[JANUARY]:[DECEMBER]]) -> 2400
B18: Security | C18: 600 | D18: 600 | E18: 600 | F18: 600 | G18: 600 | H18: 600 | I18: 600 | J18: 600 | K18: 600 | L18: 600 | M18: 600 | N18: 600 | O18: =SUM(Plan_OfficeCosts[[#This Row],[JANUARY]:[DECEMBER]]) -> 7200
B20: MARKETING COSTS | C20: =SUM(INDIRECT("Plan_MarketingCosts["&C$3&"]")) -> 8100 | D20: =SUM(INDIRECT("Plan_MarketingCosts["&D$3&"]")) -> 3100 | E20: =SUM(INDIRECT("Plan_MarketingCosts["&E$3&"]")) -> 3100 | F20: =SUM(INDIRECT("Plan_MarketingCosts["&F$3&"]")) -> 11100 | G20: =SUM(INDIRECT("Plan_MarketingCosts["&G$3&"]")) -> 3100 | H20: =SUM(INDIRECT("Plan_MarketingCosts["&H$3&"]")) -> 3900 | I20: =SUM(INDIRECT("Plan_MarketingCosts["&I$3&"]")) -> 8100 | J20: =SUM(INDIRECT("Plan_MarketingCosts["&J$3&"]")) -> 6100 | ... O20: =SUM(INDIRECT("Plan_MarketingCosts["&O$3&"]")) -> 67800
B21: MARKETING COSTS | C21: JANUARY | D21: FEBRUARY | E21: MARCH | F21: APRIL | G21: MAY | H21: JUNE | I21: JULY | J21: AUGUST | K21: SEPTEMBER | L21: OCTOBER | M21: NOVEMBER | N21: DECEMBER | O21: TOTAL
B22: Web site hosting | C22: 500 | D22: 500 | E22: 500 | F22: 500 | G22: 500 | H22: 500 | I22: 500 | J22: 500 | K22: 500 | L22: 500 | M22: 500 | N22: 500 | O22: =SUM(Plan_MarketingCosts[[#This Row],[JANUARY]:[DECEMBER]]) -> 6000
B23: Web site updates | C23: 200 | D23: 200 | E23: 200 | F23: 200 | G23: 200 | H23: 1000 | I23: 200 | J23: 200 | K23: 200 | L23: 200 | M23: 200 | N23: 1000 | O23: =SUM(Plan_MarketingCosts[[#This Row],[JANUARY]:[DECEMBER]]) -> 4000
B24: Collateral preparation | C24: 5000 | D24: 0 | E24: 0 | F24: 5000 | G24: 0 | H24: 0 | I24: 5000 | J24: 0 | K24: 0 | L24: 5000 | M24: 0 | N24: 0 | O24: =SUM(Plan_MarketingCosts[[#This Row],[JANUARY]:[DECEMBER]]) -> 20000
B25: Collateral printing | C25: 200 | D25: 200 | E25: 200 | F25: 200 | G25: 200 | H25: 200 | I25: 200 | J25: 200 | K25: 200 | L25: 200 | M25: 200 | N25: 200 | O25: =SUM(Plan_MarketingCosts[[#This Row],[JANUARY]:[DECEMBER]]) -> 2400
B26: Marketing events | C26: 2000 | D26: 2000 | E26: 2000 | F26: 5000 | G26: 2000 | H26: 2000 | I26: 2000 | J26: 5000 | K26: 2000 | L26: 2000 | M26: 2000 | N26: 5000 | O26: =SUM(Plan_MarketingCosts[[#This Row],[JANUARY]:[DECEMBER]]) -> 33000
B27: Miscellaneous expenses | C27: 200 | D27: 200 | E27: 200 | F27: 200 | G27: 200 | H27: 200 | I27: 200 | J27: 200 | K27: 200 | L27: 200 | M27: 200 | N27: 200 | O27: =SUM(Plan_MarketingCosts[[#This Row],[JANUARY]:[DECEMBER]]) -> 2400
B29: TRAINING / TRAVEL | C29: =SUM(INDIRECT("Plan_TrainingTravel["&C$3&"]")) -> 4000 | D29: =SUM(INDIRECT("Plan_TrainingTravel["&D$3&"]")) -> 4000 | E29: =SUM(INDIRECT("Plan_TrainingTravel["&E$3&"]")) -> 4000 | F29: =SUM(INDIRECT("Plan_TrainingTravel["&F$3&"]")) -> 4000 | G29: =SUM(INDIRECT("Plan_TrainingTravel["&G$3&"]")) -> 4000 | H29: =SUM(INDIRECT("Plan_TrainingTravel["&H$3&"]")) -> 4000 | I29: =SUM(INDIRECT("Plan_TrainingTravel["&I$3&"]")) -> 4000 | J29: =SUM(INDIRECT("Plan_TrainingTravel["&J$3&"]")) -> 4000 | ... O29: =SUM(INDIRECT("Plan_TrainingTravel["&O$3&"]")) -> 48000
B30: TRAINING/TRAVEL | C30: JANUARY | D30: FEBRUARY | E30: MARCH | F30: APRIL | G30: MAY | H30: JUNE | I30: JULY | J30: AUGUST | K30: SEPTEMBER | L30: OCTOBER | M30: NOVEMBER | N30: DECEMBER | O30: TOTAL
B31: Training classes | C31: 2000 | D31: 2000 | E31: 2000 | F31: 2000 | G31: 2000 | H31: 2000 | I31: 2000 | J31: 2000 | K31: 2000 | L31: 2000 | M31: 2000 | N31: 2000 | O31: =SUM(Plan_TrainingTravel[[#This Row],[JANUARY]:[DECEMBER]]) -> 24000
B32: Travel costs | C32: 2000 | D32: 2000 | E32: 2000 | F32: 2000 | G32: 2000 | H32: 2000 | I32: 2000 | J32: 2000 | K32: 2000 | L32: 2000 | M32: 2000 | N32: 2000 | O32: =SUM(Plan_TrainingTravel[[#This Row],[JANUARY]:[DECEMBER]]) -> 24000
B34: MONTHLY TOTAL | C34: =C4+C9+C20+C29 -> 131420 | D34: =D4+D9+D20+D29 -> 126820 | E34: =E4+E9+E20+E29 -> 126820 | F34: =F4+F9+F20+F29 -> 137695 | G34: =G4+G9+G20+G29 -> 129695 | H34: =H4+H9+H20+H29 -> 130495 | I34: =I4+I9+I20+I29 -> 134695 | J34: =J4+J9+J20+J29 -> 138918 | ... O34: =O4+O9+O20+O29 -> 1609630

Sheet Actual Expenses
B1: ACTUAL EXPENSES
C3: January | D3: February | E3: March | F3: April | G3: May | H3: June | I3: July | J3: August | K3: September | L3: October | M3: November | N3: December | O3: Total
B4: EMPLOYEE COSTS | C4: =SUM(INDIRECT("Actual_EmployeeCosts["&C$3&"]")) -> 107950 | D4: =SUM(INDIRECT("Actual_EmployeeCosts["&D$3&"]")) -> 107950 | E4: =SUM(INDIRECT("Actual_EmployeeCosts["&E$3&"]")) -> 107950 | F4: =SUM(INDIRECT("Actual_EmployeeCosts["&F$3&"]")) -> 111760 | G4: =SUM(INDIRECT("Actual_EmployeeCosts["&G$3&"]")) -> 111760 | H4: =SUM(INDIRECT("Actual_EmployeeCosts["&H$3&"]")) -> 111760 | I4: =SUM(INDIRECT("Actual_EmployeeCosts["&I$3&"]")) -> 112800 | J4: =SUM(INDIRECT("Actual_EmployeeCosts["&J$3&"]")) -> 107950 | ... O4: =SUM(INDIRECT("Actual_EmployeeCosts["&O$3&"]")) -> 1324150
B5: EMPLOYEE COSTS | C5: JANUARY | D5: FEBRUARY | E5: MARCH | F5: APRIL | G5: MAY | H5: JUNE | I5: JULY | J5: AUGUST | K5: SEPTEMBER | L5: OCTOBER | M5: NOVEMBER | N5: DECEMBER | O5: TOTAL
B6: Wages | C6: 85000 | D6: 85000 | E6: 85000 | F6: 88000 | G6: 88000 | H6: 88000 | I6: 89000 | J6: 85000 | K6: 88000 | L6: 89000 | M6: 85000 | N6: 88000 | O6: =SUM(Actual_EmployeeCosts[[#This Row],[JANUARY]:[DECEMBER]]) -> 1043000
B7: Benefits | C7: 22950 | D7: 22950 | E7: 22950 | F7: 23760 | G7: 23760 | H7: 23760 | I7: 23800 | J7: 22950 | K7: 23760 | L7: 23800 | M7: 22950 | N7: 23760 | O7: =SUM(Actual_EmployeeCosts[[#This Row],[JANUARY]:[DECEMBER]]) -> 281150
B9: OFFICE COSTS | C9: =SUM(INDIRECT("Actual_OfficeCosts["&C$3&"]")) -> 11387 | D9: =SUM(INDIRECT("Actual_OfficeCosts["&D$3&"]")) -> 11698 | E9: =SUM(INDIRECT("Actual_OfficeCosts["&E$3&"]")) -> 11692 | F9: =SUM(INDIRECT("Actual_OfficeCosts["&F$3&"]")) -> 11611 | G9: =SUM(INDIRECT("Actual_OfficeCosts["&G$3&"]")) -> 11508 | H9: =SUM(INDIRECT("Actual_OfficeCosts["&H$3&"]")) -> 11454 | I9: =SUM(INDIRECT("Actual_OfficeCosts["&I$3&"]")) -> 12070 | J9: =SUM(INDIRECT("Actual_OfficeCosts["&J$3&"]")) -> 11694 | ... O9: =SUM(INDIRECT("Actual_OfficeCosts["&O$3&"]")) -> 139583
B10: OFFICE COSTS | C10: JANUARY | D10: FEBRUARY | E10: MARCH | F10: APRIL | G10: MAY | H10: JUNE | I10: JULY | J10: AUGUST | K10: SEPTEMBER | L10: OCTOBER | M10: NOVEMBER | N10: DECEMBER | O10: TOTAL
B11: Office lease | C11: 9800 | D11: 9800 | E11: 9800 | F11: 9800 | G11: 9800 | H11: 9800 | I11: 9800 | J11: 9800 | K11: 9800 | L11: 9800 | M11: 9800 | N11: 9800 | O11: =SUM(Actual_OfficeCosts[[#This Row],[JANUARY]:[DECEMBER]]) -> 117600
B12: Gas | C12: 4 | D12: 430 | E12: 385 | F12: 230 | G12: 87 | H12: 88 | I12: 500 | J12: 320 | K12: 90 | L12: 278 | M12: 378 | N12: 400 | O12: =SUM(Actual_OfficeCosts[[#This Row],[JANUARY]:[DECEMBER]]) -> 3190
B13: Electric | C13: 288 | D13: 278 | E13: 268 | F13: 299 | G13: 306 | H13: 290 | I13: 408 | J13: 275 | K13: 445 | L13: 245 | M13: 280 | N13: 269 | O13: =SUM(Actual_OfficeCosts[[#This Row],[JANUARY]:[DECEMBER]]) -> 3651
B14: Water | C14: 35 | D14: 33 | E14: 34 | F14: 36 | G14: 34 | H14: 36 | I14: 37 | J14: 34 | K14: 30 | L14: 32 | M14: 34 | N14: 36 | O14: =SUM(Actual_OfficeCosts[[#This Row],[JANUARY]:[DECEMBER]]) -> 411
B15: Telephone | C15: 224 | D15: 235 | E15: 265 | F15: 245 | G15: 245 | H15: 220 | I15: 245 | J15: 240 | K15: 230 | L15: 225 | M15: 23 | N15: 210 | O15: =SUM(Actual_OfficeCosts[[#This Row],[JANUARY]:[DECEMBER]]) -> 2607
B16: Internet access | C16: 180 | D16: 180 | E16: 180 | F16: 180 | G16: 180 | H16: 180 | I16: 180 | J16: 180 | K16: 180 | L16: 180 | M16: 180 | N16: 180 | O16: =SUM(Actual_OfficeCosts[[#This Row],[JANUARY]:[DECEMBER]]) -> 2160
B17: Office supplies | C17: 256 | D17: 142 | E17: 160 | F17: 221 | G17: 256 | H17: 240 | I17: 300 | J17: 245 | K17: 234 | L17: 270 | M17: 205 | N17: 235 | O17: =SUM(Actual_OfficeCosts[[#This Row],[JANUARY]:[DECEMBER]]) -> 2764
B18: Security | C18: 600 | D18: 600 | E18: 600 | F18: 600 | G18: 600 | H18: 600 | I18: 600 | J18: 600 | K18: 600 | L18: 600 | M18: 600 | N18: 600 | O18: =SUM(Actual_OfficeCosts[[#This Row],[JANUARY]:[DECEMBER]]) -> 7200
B20: MARKETING COSTS | C20: =SUM(INDIRECT("Actual_MarketingCosts["&C$3&"]")) -> 7545 | D20: =SUM(INDIRECT("Actual_MarketingCosts["&D$3&"]")) -> 3556 | E20: =SUM(INDIRECT("Actual_MarketingCosts["&E$3&"]")) -> 3123 | F20: =SUM(INDIRECT("Actual_MarketingCosts["&F$3&"]")) -> 11223 | G20: =SUM(INDIRECT("Actual_MarketingCosts["&G$3&"]")) -> 2987 | H20: =SUM(INDIRECT("Actual_MarketingCosts["&H$3&"]")) -> 4725 | I20: =SUM(INDIRECT("Actual_MarketingCosts["&I$3&"]")) -> 8200 | J20: =SUM(INDIRECT("Actual_MarketingCosts["&J$3&"]")) -> 3240 | ... O20: =SUM(INDIRECT("Actual_MarketingCosts["&O$3&"]")) -> 69039
B21: MARKETING COSTS | C21: JANUARY | D21: FEBRUARY | E21: MARCH | F21: APRIL | G21: MAY | H21: JUNE | I21: JULY | J21: AUGUST | K21: SEPTEMBER | L21: OCTOBER | M21: NOVEMBER | N21: DECEMBER | O21: TOTAL
B22: Web site hosting | C22: 500 | D22: 500 | E22: 500 | F22: 500 | G22: 500 | H22: 500 | I22: 550 | J22: 550 | K22: 550 | L22: 550 | M22: 550 | N22: 550 | O22: =SUM(Actual_MarketingCosts[[#This Row],[JANUARY]:[DECEMBER]]) -> 6300
B23: Web site updates | C23: 200 | D23: 200 | E23: 200 | F23: 200 | G23: 200 | H23: 1500 | I23: 200 | J23: 200 | K23: 200 | L23: 200 | M23: 200 | N23: 200 | O23: =SUM(Actual_MarketingCosts[[#This Row],[JANUARY]:[DECEMBER]]) -> 3700
B24: Collateral preparation | C24: 4800 | D24: 0 | E24: 0 | F24: 5500 | G24: 0 | H24: 0 | I24: 0 | J24: 0 | K24: 6000 | L24: 0 | M24: 1500 | N24: 3000 | O24: =SUM(Actual_MarketingCosts[[#This Row],[JANUARY]:[DECEMBER]]) -> 20800
B25: Collateral printing | C25: 100 | D25: 500 | E25: 100 | F25: 100 | G25: 600 | H25: 180 | I25: 200 | J25: 150 | K25: 100 | L25: 200 | M25: 250 | N25: 150 | O25: =SUM(Actual_MarketingCosts[[#This Row],[JANUARY]:[DECEMBER]]) -> 2630
B26: Marketing events | C26: 1800 | D26: 2200 | E26: 2200 | F26: 4700 | G26: 1500 | H26: 2300 | I26: 7000 | J26: 2000 | K26: 2500 | L26: 3500 | M26: 2000 | N26: 1500 | O26: =SUM(Actual_MarketingCosts[[#This Row],[JANUARY]:[DECEMBER]]) -> 33200
B27: Miscellaneous expenses | C27: 145 | D27: 156 | E27: 123 | F27: 223 | G27: 187 | H27: 245 | I27: 250 | J27: 340 | K27: 220 | L27: 150 | M27: 170 | N27: 200 | O27: =SUM(Actual_MarketingCosts[[#This Row],[JANUARY]:[DECEMBER]]) -> 2409
B29: TRAINING / TRAVEL | C29: =SUM(INDIRECT("Actual_TrainingTravel["&C$3&"]")) -> 2800 | D29: =SUM(INDIRECT("Actual_TrainingTravel["&D$3&"]")) -> 4600 | E29: =SUM(INDIRECT("Actual_TrainingTravel["&E$3&"]")) -> 2800 | F29: =SUM(INDIRECT("Actual_TrainingTravel["&F$3&"]")) -> 2800 | G29: =SUM(INDIRECT("Actual_TrainingTravel["&G$3&"]")) -> 2000 | H29: =SUM(INDIRECT("Actual_TrainingTravel["&H$3&"]")) -> 6300 | I29: =SUM(INDIRECT("Actual_TrainingTravel["&I$3&"]")) -> 3500 | J29: =SUM(INDIRECT("Actual_TrainingTravel["&J$3&"]")) -> 4500 | ... O29: =SUM(INDIRECT("Actual_TrainingTravel["&O$3&"]")) -> 45400
B30: TRAINING/TRAVEL | C30: JANUARY | D30: FEBRUARY | E30: MARCH | F30: APRIL | G30: MAY | H30: JUNE | I30: JULY | J30: AUGUST | K30: SEPTEMBER | L30: OCTOBER | M30: NOVEMBER | N30: DECEMBER | O30: TOTAL
B31: Training classes | C31: 1600 | D31: 2400 | E31: 1400 | F31: 1600 | G31: 1200 | H31: 2800 | I31: 1500 | J31: 3000 | K31: 1600 | L31: 1200 | M31: 3400 | N31: 200 | O31: =SUM(Actual_TrainingTravel[[#This Row],[JANUARY]:[DECEMBER]]) -> 21900
B32: Travel costs | C32: 1200 | D32: 2200 | E32: 1400 | F32: 1200 | G32: 800 | H32: 3500 | I32: 2000 | J32: 1500 | K32: 2600 | L32: 4000 | M32: 1000 | N32: 2100 | O32: =SUM(Actual_TrainingTravel[[#This Row],[JANUARY]:[DECEMBER]]) -> 23500
B34: MONTHLY TOTAL | C34: =C4+C9+C20+C29 -> 129682 | D34: =D4+D9+D20+D29 -> 127804 | E34: =E4+E9+E20+E29 -> 125565 | F34: =F4+F9+F20+F29 -> 137394 | G34: =G4+G9+G20+G29 -> 128255 | H34: =H4+H9+H20+H29 -> 134239 | I34: =I4+I9+I20+I29 -> 136570 | J34: =J4+J9+J20+J29 -> 127384 | ... O34: =O4+O9+O20+O29 -> 1578172

Sheet Expense Variances
B1: EXPENSE VARIANCES
B2: Note: Negative values mean actual expense is higher than planned expense.
C3: January | D3: February | E3: March | F3: April | G3: May | H3: June | I3: July | J3: August | K3: September | L3: October | M3: November | N3: December | O3: Total
B4: EMPLOYEE COSTS | C4: =SUM(INDIRECT("Var_EmployeeCosts["&C$3&"]")) -> 0 | D4: =SUM(INDIRECT("Var_EmployeeCosts["&D$3&"]")) -> 0 | E4: =SUM(INDIRECT("Var_EmployeeCosts["&E$3&"]")) -> 0 | F4: =SUM(INDIRECT("Var_EmployeeCosts["&F$3&"]")) -> -635 | G4: =SUM(INDIRECT("Var_EmployeeCosts["&G$3&"]")) -> -635 | H4: =SUM(INDIRECT("Var_EmployeeCosts["&H$3&"]")) -> -635 | I4: =SUM(INDIRECT("Var_EmployeeCosts["&I$3&"]")) -> -1675 | J4: =SUM(INDIRECT("Var_EmployeeCosts["&J$3&"]")) -> 9398 | ... O4: =SUM(INDIRECT("Var_EmployeeCosts["&O$3&"]")) -> 30940
B5: EMPLOYEE COSTS | C5: JANUARY | D5: FEBRUARY | E5: MARCH | F5: APRIL | G5: MAY | H5: JUNE | I5: JULY | J5: AUGUST | K5: SEPTEMBER | L5: OCTOBER | M5: NOVEMBER | N5: DECEMBER | O5: TOTAL
B6: Wages | C6: =IF(INDIRECT("Actual_EmployeeCosts["&C$3&"]")="","",INDIRECT("Plan_EmployeeCosts["&C$3&"]")-INDIRECT("Actual_EmployeeCosts["&C$3&"]")) -> 0 | D6: =IF(INDIRECT("Actual_EmployeeCosts["&D$3&"]")="","",INDIRECT("Plan_EmployeeCosts["&D$3&"]")-INDIRECT("Actual_EmployeeCosts["&D$3&"]")) -> 0 | E6: =IF(INDIRECT("Actual_EmployeeCosts["&E$3&"]")="","",INDIRECT("Plan_EmployeeCosts["&E$3&"]")-INDIRECT("Actual_EmployeeCosts["&E$3&"]")) -> 0 | F6: =IF(INDIRECT("Actual_EmployeeCosts["&F$3&"]")="","",INDIRECT("Plan_EmployeeCosts["&F$3&"]")-INDIRECT("Actual_EmployeeCosts["&F$3&"]")) -> -500 | G6: =IF(INDIRECT("Actual_EmployeeCosts["&G$3&"]")="","",INDIRECT("Plan_EmployeeCosts["&G$3&"]")-INDIRECT("Actual_EmployeeCosts["&G$3&"]")) -> -500 | H6: =IF(INDIRECT("Actual_EmployeeCosts["&H$3&"]")="","",INDIRECT("Plan_EmployeeCosts["&H$3&"]")-INDIRECT("Actual_EmployeeCosts["&H$3&"]")) -> -500 | I6: =IF(INDIRECT("Actual_EmployeeCosts["&I$3&"]")="","",INDIRECT("Plan_EmployeeCosts["&I$3&"]")-INDIRECT("Actual_EmployeeCosts["&I$3&"]")) -> -1500 | J6: =IF(INDIRECT("Actual_EmployeeCosts["&J$3&"]")="","",INDIRECT("Plan_EmployeeCosts["&J$3&"]")-INDIRECT("Actual_EmployeeCosts["&J$3&"]")) -> 7400 | ... N6: =IF(INDIRECT("Actual_EmployeeCosts["&N$3&"]")="","",INDIRECT("Plan_EmployeeCosts["&N$3&"]")-INDIRECT("Actual_EmployeeCosts["&N$3&"]")) -> 4400 | O6: =SUM(Var_EmployeeCosts[[#This Row],[JANUARY]:[DECEMBER]]) -> 24000
B7: Benefits | C7: =IF(INDIRECT("Actual_EmployeeCosts["&C$3&"]")="","",INDIRECT("Plan_EmployeeCosts["&C$3&"]")-INDIRECT("Actual_EmployeeCosts["&C$3&"]")) -> 0 | D7: =IF(INDIRECT("Actual_EmployeeCosts["&D$3&"]")="","",INDIRECT("Plan_EmployeeCosts["&D$3&"]")-INDIRECT("Actual_EmployeeCosts["&D$3&"]")) -> 0 | E7: =IF(INDIRECT("Actual_EmployeeCosts["&E$3&"]")="","",INDIRECT("Plan_EmployeeCosts["&E$3&"]")-INDIRECT("Actual_EmployeeCosts["&E$3&"]")) -> 0 | F7: =IF(INDIRECT("Actual_EmployeeCosts["&F$3&"]")="","",INDIRECT("Plan_EmployeeCosts["&F$3&"]")-INDIRECT("Actual_EmployeeCosts["&F$3&"]")) -> -135 | G7: =IF(INDIRECT("Actual_EmployeeCosts["&G$3&"]")="","",INDIRECT("Plan_EmployeeCosts["&G$3&"]")-INDIRECT("Actual_EmployeeCosts["&G$3&"]")) -> -135 | H7: =IF(INDIRECT("Actual_EmployeeCosts["&H$3&"]")="","",INDIRECT("Plan_EmployeeCosts["&H$3&"]")-INDIRECT("Actual_EmployeeCosts["&H$3&"]")) -> -135 | I7: =IF(INDIRECT("Actual_EmployeeCosts["&I$3&"]")="","",INDIRECT("Plan_EmployeeCosts["&I$3&"]")-INDIRECT("Actual_EmployeeCosts["&I$3&"]")) -> -175 | J7: =IF(INDIRECT("Actual_EmployeeCosts["&J$3&"]")="","",INDIRECT("Plan_EmployeeCosts["&J$3&"]")-INDIRECT("Actual_EmployeeCosts["&J$3&"]")) -> 1998 | ... N7: =IF(INDIRECT("Actual_EmployeeCosts["&N$3&"]")="","",INDIRECT("Plan_EmployeeCosts["&N$3&"]")-INDIRECT("Actual_EmployeeCosts["&N$3&"]")) -> 1188 | O7: =SUM(Var_EmployeeCosts[[#This Row],[JANUARY]:[DECEMBER]]) -> 6940
B9: OFFICE COSTS | C9: =SUM(INDIRECT("Var_OfficeCosts["&C$3&"]")) -> -17 | D9: =SUM(INDIRECT("Var_OfficeCosts["&D$3&"]")) -> 72 | E9: =SUM(INDIRECT("Var_OfficeCosts["&E$3&"]")) -> 78 | F9: =SUM(INDIRECT("Var_OfficeCosts["&F$3&"]")) -> -141 | G9: =SUM(INDIRECT("Var_OfficeCosts["&G$3&"]")) -> -38 | H9: =SUM(INDIRECT("Var_OfficeCosts["&H$3&"]")) -> 16 | I9: =SUM(INDIRECT("Var_OfficeCosts["&I$3&"]")) -> -600 | J9: =SUM(INDIRECT("Var_OfficeCosts["&J$3&"]")) -> -224 | ... O9: =SUM(INDIRECT("Var_OfficeCosts["&O$3&"]")) -> -843
B10: OFFICE COSTS | C10: JANUARY | D10: FEBRUARY | E10: MARCH | F10: APRIL | G10: MAY | H10: JUNE | I10: JULY | J10: AUGUST | K10: SEPTEMBER | L10: OCTOBER | M10: NOVEMBER | N10: DECEMBER | O10: TOTAL
B11: Office lease | C11: =IF(INDIRECT("Actual_OfficeCosts["&C$3&"]")="","",INDIRECT("Plan_OfficeCosts["&C$3&"]")-INDIRECT("Actual_OfficeCosts["&C$3&"]")) -> 0 | D11: =IF(INDIRECT("Actual_OfficeCosts["&D$3&"]")="","",INDIRECT("Plan_OfficeCosts["&D$3&"]")-INDIRECT("Actual_OfficeCosts["&D$3&"]")) -> 0 | E11: =IF(INDIRECT("Actual_OfficeCosts["&E$3&"]")="","",INDIRECT("Plan_OfficeCosts["&E$3&"]")-INDIRECT("Actual_OfficeCosts["&E$3&"]")) -> 0 | F11: =IF(INDIRECT("Actual_OfficeCosts["&F$3&"]")="","",INDIRECT("Plan_OfficeCosts["&F$3&"]")-INDIRECT("Actual_OfficeCosts["&F$3&"]")) -> 0 | G11: =IF(INDIRECT("Actual_OfficeCosts["&G$3&"]")="","",INDIRECT("Plan_OfficeCosts["&G$3&"]")-INDIRECT("Actual_OfficeCosts["&G$3&"]")) -> 0 | H11: =IF(INDIRECT("Actual_OfficeCosts["&H$3&"]")="","",INDIRECT("Plan_OfficeCosts["&H$3&"]")-INDIRECT("Actual_OfficeCosts["&H$3&"]")) -> 0 | I11: =IF(INDIRECT("Actual_OfficeCosts["&I$3&"]")="","",INDIRECT("Plan_OfficeCosts["&I$3&"]")-INDIRECT("Actual_OfficeCosts["&I$3&"]")) -> 0 | J11: =IF(INDIRECT("Actual_OfficeCosts["&J$3&"]")="","",INDIRECT("Plan_OfficeCosts["&J$3&"]")-INDIRECT("Actual_OfficeCosts["&J$3&"]")) -> 0 | ... N11: =IF(INDIRECT("Actual_OfficeCosts["&N$3&"]")="","",INDIRECT("Plan_OfficeCosts["&N$3&"]")-INDIRECT("Actual_OfficeCosts["&N$3&"]")) -> 0 | O11: =SUM(Var_OfficeCosts[[#This Row],[JANUARY]:[DECEMBER]]) -> 0
B12: Gas | C12: =IF(INDIRECT("Actual_OfficeCosts["&C$3&"]")="","",INDIRECT("Plan_OfficeCosts["&C$3&"]")-INDIRECT("Actual_OfficeCosts["&C$3&"]")) -> -4 | D12: =IF(INDIRECT("Actual_OfficeCosts["&D$3&"]")="","",INDIRECT("Plan_OfficeCosts["&D$3&"]")-INDIRECT("Actual_OfficeCosts["&D$3&"]")) -> -30 | E12: =IF(INDIRECT("Actual_OfficeCosts["&E$3&"]")="","",INDIRECT("Plan_OfficeCosts["&E$3&"]")-INDIRECT("Actual_OfficeCosts["&E$3&"]")) -> 15 | F12: =IF(INDIRECT("Actual_OfficeCosts["&F$3&"]")="","",INDIRECT("Plan_OfficeCosts["&F$3&"]")-INDIRECT("Actual_OfficeCosts["&F$3&"]")) -> -130 | G12: =IF(INDIRECT("Actual_OfficeCosts["&G$3&"]")="","",INDIRECT("Plan_OfficeCosts["&G$3&"]")-INDIRECT("Actual_OfficeCosts["&G$3&"]")) -> 13 | H12: =IF(INDIRECT("Actual_OfficeCosts["&H$3&"]")="","",INDIRECT("Plan_OfficeCosts["&H$3&"]")-INDIRECT("Actual_OfficeCosts["&H$3&"]")) -> 12 | I12: =IF(INDIRECT("Actual_OfficeCosts["&I$3&"]")="","",INDIRECT("Plan_OfficeCosts["&I$3&"]")-INDIRECT("Actual_OfficeCosts["&I$3&"]")) -> -400 | J12: =IF(INDIRECT("Actual_OfficeCosts["&J$3&"]")="","",INDIRECT("Plan_OfficeCosts["&J$3&"]")-INDIRECT("Actual_OfficeCosts["&J$3&"]")) -> -220 | ... N12: =IF(INDIRECT("Actual_OfficeCosts["&N$3&"]")="","",INDIRECT("Plan_OfficeCosts["&N$3&"]")-INDIRECT("Actual_OfficeCosts["&N$3&"]")) -> 0 | O12: =SUM(Var_OfficeCosts[[#This Row],[JANUARY]:[DECEMBER]]) -> -890
B13: Electric | C13: =IF(INDIRECT("Actual_OfficeCosts["&C$3&"]")="","",INDIRECT("Plan_OfficeCosts["&C$3&"]")-INDIRECT("Actual_OfficeCosts["&C$3&"]")) -> 12 | D13: =IF(INDIRECT("Actual_OfficeCosts["&D$3&"]")="","",INDIRECT("Plan_OfficeCosts["&D$3&"]")-INDIRECT("Actual_OfficeCosts["&D$3&"]")) -> 22 | E13: =IF(INDIRECT("Actual_OfficeCosts["&E$3&"]")="","",INDIRECT("Plan_OfficeCosts["&E$3&"]")-INDIRECT("Actual_OfficeCosts["&E$3&"]")) -> 32 | F13: =IF(INDIRECT("Actual_OfficeCosts["&F$3&"]")="","",INDIRECT("Plan_OfficeCosts["&F$3&"]")-INDIRECT("Actual_OfficeCosts["&F$3&"]")) -> 1 | G13: =IF(INDIRECT("Actual_OfficeCosts["&G$3&"]")="","",INDIRECT("Plan_OfficeCosts["&G$3&"]")-INDIRECT("Actual_OfficeCosts["&G$3&"]")) -> -6 | H13: =IF(INDIRECT("Actual_OfficeCosts["&H$3&"]")="","",INDIRECT("Plan_OfficeCosts["&H$3&"]")-INDIRECT("Actual_OfficeCosts["&H$3&"]")) -> 10 | I13: =IF(INDIRECT("Actual_OfficeCosts["&I$3&"]")="","",INDIRECT("Plan_OfficeCosts["&I$3&"]")-INDIRECT("Actual_OfficeCosts["&I$3&"]")) -> -108 | J13: =IF(INDIRECT("Actual_OfficeCosts["&J$3&"]")="","",INDIRECT("Plan_OfficeCosts["&J$3&"]")-INDIRECT("Actual_OfficeCosts["&J$3&"]")) -> 25 | ... N13: =IF(INDIRECT("Actual_OfficeCosts["&N$3&"]")="","",INDIRECT("Plan_OfficeCosts["&N$3&"]")-INDIRECT("Actual_OfficeCosts["&N$3&"]")) -> 31 | O13: =SUM(Var_OfficeCosts[[#This Row],[JANUARY]:[DECEMBER]]) -> -51
B14: Water | C14: =IF(INDIRECT("Actual_OfficeCosts["&C$3&"]")="","",INDIRECT("Plan_OfficeCosts["&C$3&"]")-INDIRECT("Actual_OfficeCosts["&C$3&"]")) -> 5 | D14: =IF(INDIRECT("Actual_OfficeCosts["&D$3&"]")="","",INDIRECT("Plan_OfficeCosts["&D$3&"]")-INDIRECT("Actual_OfficeCosts["&D$3&"]")) -> 7 | E14: =IF(INDIRECT("Actual_OfficeCosts["&E$3&"]")="","",INDIRECT("Plan_OfficeCosts["&E$3&"]")-INDIRECT("Actual_OfficeCosts["&E$3&"]")) -> 6 | F14: =IF(INDIRECT("Actual_OfficeCosts["&F$3&"]")="","",INDIRECT("Plan_OfficeCosts["&F$3&"]")-INDIRECT("Actual_OfficeCosts["&F$3&"]")) -> 4 | G14: =IF(INDIRECT("Actual_OfficeCosts["&G$3&"]")="","",INDIRECT("Plan_OfficeCosts["&G$3&"]")-INDIRECT("Actual_OfficeCosts["&G$3&"]")) -> 6 | H14: =IF(INDIRECT("Actual_OfficeCosts["&H$3&"]")="","",INDIRECT("Plan_OfficeCosts["&H$3&"]")-INDIRECT("Actual_OfficeCosts["&H$3&"]")) -> 4 | I14: =IF(INDIRECT("Actual_OfficeCosts["&I$3&"]")="","",INDIRECT("Plan_OfficeCosts["&I$3&"]")-INDIRECT("Actual_OfficeCosts["&I$3&"]")) -> 3 | J14: =IF(INDIRECT("Actual_OfficeCosts["&J$3&"]")="","",INDIRECT("Plan_OfficeCosts["&J$3&"]")-INDIRECT("Actual_OfficeCosts["&J$3&"]")) -> 6 | ... N14: =IF(INDIRECT("Actual_OfficeCosts["&N$3&"]")="","",INDIRECT("Plan_OfficeCosts["&N$3&"]")-INDIRECT("Actual_OfficeCosts["&N$3&"]")) -> 4 | O14: =SUM(Var_OfficeCosts[[#This Row],[JANUARY]:[DECEMBER]]) -> 69
B15: Telephone | C15: =IF(INDIRECT("Actual_OfficeCosts["&C$3&"]")="","",INDIRECT("Plan_OfficeCosts["&C$3&"]")-INDIRECT("Actual_OfficeCosts["&C$3&"]")) -> 26 | D15: =IF(INDIRECT("Actual_OfficeCosts["&D$3&"]")="","",INDIRECT("Plan_OfficeCosts["&D$3&"]")-INDIRECT("Actual_OfficeCosts["&D$3&"]")) -> 15 | E15: =IF(INDIRECT("Actual_OfficeCosts["&E$3&"]")="","",INDIRECT("Plan_OfficeCosts["&E$3&"]")-INDIRECT("Actual_OfficeCosts["&E$3&"]")) -> -15 | F15: =IF(INDIRECT("Actual_OfficeCosts["&F$3&"]")="","",INDIRECT("Plan_OfficeCosts["&F$3&"]")-INDIRECT("Actual_OfficeCosts["&F$3&"]")) -> 5 | G15: =IF(INDIRECT("Actual_OfficeCosts["&G$3&"]")="","",INDIRECT("Plan_OfficeCosts["&G$3&"]")-INDIRECT("Actual_OfficeCosts["&G$3&"]")) -> 5 | H15: =IF(INDIRECT("Actual_OfficeCosts["&H$3&"]")="","",INDIRECT("Plan_OfficeCosts["&H$3&"]")-INDIRECT("Actual_OfficeCosts["&H$3&"]")) -> 30 | I15: =IF(INDIRECT("Actual_OfficeCosts["&I$3&"]")="","",INDIRECT("Plan_OfficeCosts["&I$3&"]")-INDIRECT("Actual_OfficeCosts["&I$3&"]")) -> 5 | J15: =IF(INDIRECT("Actual_OfficeCosts["&J$3&"]")="","",INDIRECT("Plan_OfficeCosts["&J$3&"]")-INDIRECT("Actual_OfficeCosts["&J$3&"]")) -> 10 | ... N15: =IF(INDIRECT("Actual_OfficeCosts["&N$3&"]")="","",INDIRECT("Plan_OfficeCosts["&N$3&"]")-INDIRECT("Actual_OfficeCosts["&N$3&"]")) -> 40 | O15: =SUM(Var_OfficeCosts[[#This Row],[JANUARY]:[DECEMBER]]) -> 393
B16: Internet access | C16: =IF(INDIRECT("Actual_OfficeCosts["&C$3&"]")="","",INDIRECT("Plan_OfficeCosts["&C$3&"]")-INDIRECT("Actual_OfficeCosts["&C$3&"]")) -> 0 | D16: =IF(INDIRECT("Actual_OfficeCosts["&D$3&"]")="","",INDIRECT("Plan_OfficeCosts["&D$3&"]")-INDIRECT("Actual_OfficeCosts["&D$3&"]")) -> 0 | E16: =IF(INDIRECT("Actual_OfficeCosts["&E$3&"]")="","",INDIRECT("Plan_OfficeCosts["&E$3&"]")-INDIRECT("Actual_OfficeCosts["&E$3&"]")) -> 0 | F16: =IF(INDIRECT("Actual_OfficeCosts["&F$3&"]")="","",INDIRECT("Plan_OfficeCosts["&F$3&"]")-INDIRECT("Actual_OfficeCosts["&F$3&"]")) -> 0 | G16: =IF(INDIRECT("Actual_OfficeCosts["&G$3&"]")="","",INDIRECT("Plan_OfficeCosts["&G$3&"]")-INDIRECT("Actual_OfficeCosts["&G$3&"]")) -> 0 | H16: =IF(INDIRECT("Actual_OfficeCosts["&H$3&"]")="","",INDIRECT("Plan_OfficeCosts["&H$3&"]")-INDIRECT("Actual_OfficeCosts["&H$3&"]")) -> 0 | I16: =IF(INDIRECT("Actual_OfficeCosts["&I$3&"]")="","",INDIRECT("Plan_OfficeCosts["&I$3&"]")-INDIRECT("Actual_OfficeCosts["&I$3&"]")) -> 0 | J16: =IF(INDIRECT("Actual_OfficeCosts["&J$3&"]")="","",INDIRECT("Plan_OfficeCosts["&J$3&"]")-INDIRECT("Actual_OfficeCosts["&J$3&"]")) -> 0 | ... N16: =IF(INDIRECT("Actual_OfficeCosts["&N$3&"]")="","",INDIRECT("Plan_OfficeCosts["&N$3&"]")-INDIRECT("Actual_OfficeCosts["&N$3&"]")) -> 0 | O16: =SUM(Var_OfficeCosts[[#This Row],[JANUARY]:[DECEMBER]]) -> 0
B17: Office supplies | C17: =IF(INDIRECT("Actual_OfficeCosts["&C$3&"]")="","",INDIRECT("Plan_OfficeCosts["&C$3&"]")-INDIRECT("Actual_OfficeCosts["&C$3&"]")) -> -56 | D17: =IF(INDIRECT("Actual_OfficeCosts["&D$3&"]")="","",INDIRECT("Plan_OfficeCosts["&D$3&"]")-INDIRECT("Actual_OfficeCosts["&D$3&"]")) -> 58 | E17: =IF(INDIRECT("Actual_OfficeCosts["&E$3&"]")="","",INDIRECT("Plan_OfficeCosts["&E$3&"]")-INDIRECT("Actual_OfficeCosts["&E$3&"]")) -> 40 | F17: =IF(INDIRECT("Actual_OfficeCosts["&F$3&"]")="","",INDIRECT("Plan_OfficeCosts["&F$3&"]")-INDIRECT("Actual_OfficeCosts["&F$3&"]")) -> -21 | G17: =IF(INDIRECT("Actual_OfficeCosts["&G$3&"]")="","",INDIRECT("Plan_OfficeCosts["&G$3&"]")-INDIRECT("Actual_OfficeCosts["&G$3&"]")) -> -56 | H17: =IF(INDIRECT("Actual_OfficeCosts["&H$3&"]")="","",INDIRECT("Plan_OfficeCosts["&H$3&"]")-INDIRECT("Actual_OfficeCosts["&H$3&"]")) -> -40 | I17: =IF(INDIRECT("Actual_OfficeCosts["&I$3&"]")="","",INDIRECT("Plan_OfficeCosts["&I$3&"]")-INDIRECT("Actual_OfficeCosts["&I$3&"]")) -> -100 | J17: =IF(INDIRECT("Actual_OfficeCosts["&J$3&"]")="","",INDIRECT("Plan_OfficeCosts["&J$3&"]")-INDIRECT("Actual_OfficeCosts["&J$3&"]")) -> -45 | ... N17: =IF(INDIRECT("Actual_OfficeCosts["&N$3&"]")="","",INDIRECT("Plan_OfficeCosts["&N$3&"]")-INDIRECT("Actual_OfficeCosts["&N$3&"]")) -> -35 | O17: =SUM(Var_OfficeCosts[[#This Row],[JANUARY]:[DECEMBER]]) -> -364
B18: Security | C18: =IF(INDIRECT("Actual_OfficeCosts["&C$3&"]")="","",INDIRECT("Plan_OfficeCosts["&C$3&"]")-INDIRECT("Actual_OfficeCosts["&C$3&"]")) -> 0 | D18: =IF(INDIRECT("Actual_OfficeCosts["&D$3&"]")="","",INDIRECT("Plan_OfficeCosts["&D$3&"]")-INDIRECT("Actual_OfficeCosts["&D$3&"]")) -> 0 | E18: =IF(INDIRECT("Actual_OfficeCosts["&E$3&"]")="","",INDIRECT("Plan_OfficeCosts["&E$3&"]")-INDIRECT("Actual_OfficeCosts["&E$3&"]")) -> 0 | F18: =IF(INDIRECT("Actual_OfficeCosts["&F$3&"]")="","",INDIRECT("Plan_OfficeCosts["&F$3&"]")-INDIRECT("Actual_OfficeCosts["&F$3&"]")) -> 0 | G18: =IF(INDIRECT("Actual_OfficeCosts["&G$3&"]")="","",INDIRECT("Plan_OfficeCosts["&G$3&"]")-INDIRECT("Actual_OfficeCosts["&G$3&"]")) -> 0 | H18: =IF(INDIRECT("Actual_OfficeCosts["&H$3&"]")="","",INDIRECT("Plan_OfficeCosts["&H$3&"]")-INDIRECT("Actual_OfficeCosts["&H$3&"]")) -> 0 | I18: =IF(INDIRECT("Actual_OfficeCosts["&I$3&"]")="","",INDIRECT("Plan_OfficeCosts["&I$3&"]")-INDIRECT("Actual_OfficeCosts["&I$3&"]")) -> 0 | J18: =IF(INDIRECT("Actual_OfficeCosts["&J$3&"]")="","",INDIRECT("Plan_OfficeCosts["&J$3&"]")-INDIRECT("Actual_OfficeCosts["&J$3&"]")) -> 0 | ... N18: =IF(INDIRECT("Actual_OfficeCosts["&N$3&"]")="","",INDIRECT("Plan_OfficeCosts["&N$3&"]")-INDIRECT("Actual_OfficeCosts["&N$3&"]")) -> 0 | O18: =SUM(Var_OfficeCosts[[#This Row],[JANUARY]:[DECEMBER]]) -> 0
B20: MARKETING COSTS | C20: =SUM(INDIRECT("Var_MarketingCosts["&C$3&"]")) -> 555 | D20: =SUM(INDIRECT("Var_MarketingCosts["&D$3&"]")) -> -456 | E20: =SUM(INDIRECT("Var_MarketingCosts["&E$3&"]")) -> -23 | F20: =SUM(INDIRECT("Var_MarketingCosts["&F$3&"]")) -> -123 | G20: =SUM(INDIRECT("Var_MarketingCosts["&G$3&"]")) -> 113 | H20: =SUM(INDIRECT("Var_MarketingCosts["&H$3&"]")) -> -825 | I20: =SUM(INDIRECT("Var_MarketingCosts["&I$3&"]")) -> -100 | J20: =SUM(INDIRECT("Var_MarketingCosts["&J$3&"]")) -> 2860 | ... O20: =SUM(INDIRECT("Var_MarketingCosts["&O$3&"]")) -> -1239
B21: MARKETING COSTS | C21: JANUARY | D21: FEBRUARY | E21: MARCH | F21: APRIL | G21: MAY | H21: JUNE | I21: JULY | J21: AUGUST | K21: SEPTEMBER | L21: OCTOBER | M21: NOVEMBER | N21: DECEMBER | O21: TOTAL
B22: Web site hosting | C22: =IF(INDIRECT("Actual_MarketingCosts["&C$3&"]")="","",INDIRECT("Plan_MarketingCosts["&C$3&"]")-INDIRECT("Actual_MarketingCosts["&C$3&"]")) -> 0 | D22: =IF(INDIRECT("Actual_MarketingCosts["&D$3&"]")="","",INDIRECT("Plan_MarketingCosts["&D$3&"]")-INDIRECT("Actual_MarketingCosts["&D$3&"]")) -> 0 | E22: =IF(INDIRECT("Actual_MarketingCosts["&E$3&"]")="","",INDIRECT("Plan_MarketingCosts["&E$3&"]")-INDIRECT("Actual_MarketingCosts["&E$3&"]")) -> 0 | F22: =IF(INDIRECT("Actual_MarketingCosts["&F$3&"]")="","",INDIRECT("Plan_MarketingCosts["&F$3&"]")-INDIRECT("Actual_MarketingCosts["&F$3&"]")) -> 0 | G22: =IF(INDIRECT("Actual_MarketingCosts["&G$3&"]")="","",INDIRECT("Plan_MarketingCosts["&G$3&"]")-INDIRECT("Actual_MarketingCosts["&G$3&"]")) -> 0 | H22: =IF(INDIRECT("Actual_MarketingCosts["&H$3&"]")="","",INDIRECT("Plan_MarketingCosts["&H$3&"]")-INDIRECT("Actual_MarketingCosts["&H$3&"]")) -> 0 | I22: =IF(INDIRECT("Actual_MarketingCosts["&I$3&"]")="","",INDIRECT("Plan_MarketingCosts["&I$3&"]")-INDIRECT("Actual_MarketingCosts["&I$3&"]")) -> -50 | J22: =IF(INDIRECT("Actual_MarketingCosts["&J$3&"]")="","",INDIRECT("Plan_MarketingCosts["&J$3&"]")-INDIRECT("Actual_MarketingCosts["&J$3&"]")) -> -50 | ... N22: =IF(INDIRECT("Actual_MarketingCosts["&N$3&"]")="","",INDIRECT("Plan_MarketingCosts["&N$3&"]")-INDIRECT("Actual_MarketingCosts["&N$3&"]")) -> -50 | O22: =SUM(Var_MarketingCosts[[#This Row],[JANUARY]:[DECEMBER]]) -> -300
B23: Web site updates | C23: =IF(INDIRECT("Actual_MarketingCosts["&C$3&"]")="","",INDIRECT("Plan_MarketingCosts["&C$3&"]")-INDIRECT("Actual_MarketingCosts["&C$3&"]")) -> 0 | D23: =IF(INDIRECT("Actual_MarketingCosts["&D$3&"]")="","",INDIRECT("Plan_MarketingCosts["&D$3&"]")-INDIRECT("Actual_MarketingCosts["&D$3&"]")) -> 0 | E23: =IF(INDIRECT("Actual_MarketingCosts["&E$3&"]")="","",INDIRECT("Plan_MarketingCosts["&E$3&"]")-INDIRECT("Actual_MarketingCosts["&E$3&"]")) -> 0 | F23: =IF(INDIRECT("Actual_MarketingCosts["&F$3&"]")="","",INDIRECT("Plan_MarketingCosts["&F$3&"]")-INDIRECT("Actual_MarketingCosts["&F$3&"]")) -> 0 | G23: =IF(INDIRECT("Actual_MarketingCosts["&G$3&"]")="","",INDIRECT("Plan_MarketingCosts["&G$3&"]")-INDIRECT("Actual_MarketingCosts["&G$3&"]")) -> 0 | H23: =IF(INDIRECT("Actual_MarketingCosts["&H$3&"]")="","",INDIRECT("Plan_MarketingCosts["&H$3&"]")-INDIRECT("Actual_MarketingCosts["&H$3&"]")) -> -500 | I23: =IF(INDIRECT("Actual_MarketingCosts["&I$3&"]")="","",INDIRECT("Plan_MarketingCosts["&I$3&"]")-INDIRECT("Actual_MarketingCosts["&I$3&"]")) -> 0 | J23: =IF(INDIRECT("Actual_MarketingCosts["&J$3&"]")="","",INDIRECT("Plan_MarketingCosts["&J$3&"]")-INDIRECT("Actual_MarketingCosts["&J$3&"]")) -> 0 | ... N23: =IF(INDIRECT("Actual_MarketingCosts["&N$3&"]")="","",INDIRECT("Plan_MarketingCosts["&N$3&"]")-INDIRECT("Actual_MarketingCosts["&N$3&"]")) -> 800 | O23: =SUM(Var_MarketingCosts[[#This Row],[JANUARY]:[DECEMBER]]) -> 300
B24: Collateral preparation | C24: =IF(INDIRECT("Actual_MarketingCosts["&C$3&"]")="","",INDIRECT("Plan_MarketingCosts["&C$3&"]")-INDIRECT("Actual_MarketingCosts["&C$3&"]")) -> 200 | D24: =IF(INDIRECT("Actual_MarketingCosts["&D$3&"]")="","",INDIRECT("Plan_MarketingCosts["&D$3&"]")-INDIRECT("Actual_MarketingCosts["&D$3&"]")) -> 0 | E24: =IF(INDIRECT("Actual_MarketingCosts["&E$3&"]")="","",INDIRECT("Plan_MarketingCosts["&E$3&"]")-INDIRECT("Actual_MarketingCosts["&E$3&"]")) -> 0 | F24: =IF(INDIRECT("Actual_MarketingCosts["&F$3&"]")="","",INDIRECT("Plan_MarketingCosts["&F$3&"]")-INDIRECT("Actual_MarketingCosts["&F$3&"]")) -> -500 | G24: =IF(INDIRECT("Actual_MarketingCosts["&G$3&"]")="","",INDIRECT("Plan_MarketingCosts["&G$3&"]")-INDIRECT("Actual_MarketingCosts["&G$3&"]")) -> 0 | H24: =IF(INDIRECT("Actual_MarketingCosts["&H$3&"]")="","",INDIRECT("Plan_MarketingCosts["&H$3&"]")-INDIRECT("Actual_MarketingCosts["&H$3&"]")) -> 0 | I24: =IF(INDIRECT("Actual_MarketingCosts["&I$3&"]")="","",INDIRECT("Plan_MarketingCosts["&I$3&"]")-INDIRECT("Actual_MarketingCosts["&I$3&"]")) -> 5000 | J24: =IF(INDIRECT("Actual_MarketingCosts["&J$3&"]")="","",INDIRECT("Plan_MarketingCosts["&J$3&"]")-INDIRECT("Actual_MarketingCosts["&J$3&"]")) -> 0 | ... N24: =IF(INDIRECT("Actual_MarketingCosts["&N$3&"]")="","",INDIRECT("Plan_MarketingCosts["&N$3&"]")-INDIRECT("Actual_MarketingCosts["&N$3&"]")) -> -3000 | O24: =SUM(Var_MarketingCosts[[#This Row],[JANUARY]:[DECEMBER]]) -> -800
B25: Collateral printing | C25: =IF(INDIRECT("Actual_MarketingCosts["&C$3&"]")="","",INDIRECT("Plan_MarketingCosts["&C$3&"]")-INDIRECT("Actual_MarketingCosts["&C$3&"]")) -> 100 | D25: =IF(INDIRECT("Actual_MarketingCosts["&D$3&"]")="","",INDIRECT("Plan_MarketingCosts["&D$3&"]")-INDIRECT("Actual_MarketingCosts["&D$3&"]")) -> -300 | E25: =IF(INDIRECT("Actual_MarketingCosts["&E$3&"]")="","",INDIRECT("Plan_MarketingCosts["&E$3&"]")-INDIRECT("Actual_MarketingCosts["&E$3&"]")) -> 100 | F25: =IF(INDIRECT("Actual_MarketingCosts["&F$3&"]")="","",INDIRECT("Plan_MarketingCosts["&F$3&"]")-INDIRECT("Actual_MarketingCosts["&F$3&"]")) -> 100 | G25: =IF(INDIRECT("Actual_MarketingCosts["&G$3&"]")="","",INDIRECT("Plan_MarketingCosts["&G$3&"]")-INDIRECT("Actual_MarketingCosts["&G$3&"]")) -> -400 | H25: =IF(INDIRECT("Actual_MarketingCosts["&H$3&"]")="","",INDIRECT("Plan_MarketingCosts["&H$3&"]")-INDIRECT("Actual_MarketingCosts["&H$3&"]")) -> 20 | I25: =IF(INDIRECT("Actual_MarketingCosts["&I$3&"]")="","",INDIRECT("Plan_MarketingCosts["&I$3&"]")-INDIRECT("Actual_MarketingCosts["&I$3&"]")) -> 0 | J25: =IF(INDIRECT("Actual_MarketingCosts["&J$3&"]")="","",INDIRECT("Plan_MarketingCosts["&J$3&"]")-INDIRECT("Actual_MarketingCosts["&J$3&"]")) -> 50 | ... N25: =IF(INDIRECT("Actual_MarketingCosts["&N$3&"]")="","",INDIRECT("Plan_MarketingCosts["&N$3&"]")-INDIRECT("Actual_MarketingCosts["&N$3&"]")) -> 50 | O25: =SUM(Var_MarketingCosts[[#This Row],[JANUARY]:[DECEMBER]]) -> -230
B26: Marketing events | C26: =IF(INDIRECT("Actual_MarketingCosts["&C$3&"]")="","",INDIRECT("Plan_MarketingCosts["&C$3&"]")-INDIRECT("Actual_MarketingCosts["&C$3&"]")) -> 200 | D26: =IF(INDIRECT("Actual_MarketingCosts["&D$3&"]")="","",INDIRECT("Plan_MarketingCosts["&D$3&"]")-INDIRECT("Actual_MarketingCosts["&D$3&"]")) -> -200 | E26: =IF(INDIRECT("Actual_MarketingCosts["&E$3&"]")="","",INDIRECT("Plan_MarketingCosts["&E$3&"]")-INDIRECT("Actual_MarketingCosts["&E$3&"]")) -> -200 | F26: =IF(INDIRECT("Actual_MarketingCosts["&F$3&"]")="","",INDIRECT("Plan_MarketingCosts["&F$3&"]")-INDIRECT("Actual_MarketingCosts["&F$3&"]")) -> 300 | G26: =IF(INDIRECT("Actual_MarketingCosts["&G$3&"]")="","",INDIRECT("Plan_MarketingCosts["&G$3&"]")-INDIRECT("Actual_MarketingCosts["&G$3&"]")) -> 500 | H26: =IF(INDIRECT("Actual_MarketingCosts["&H$3&"]")="","",INDIRECT("Plan_MarketingCosts["&H$3&"]")-INDIRECT("Actual_MarketingCosts["&H$3&"]")) -> -300 | I26: =IF(INDIRECT("Actual_MarketingCosts["&I$3&"]")="","",INDIRECT("Plan_MarketingCosts["&I$3&"]")-INDIRECT("Actual_MarketingCosts["&I$3&"]")) -> -5000 | J26: =IF(INDIRECT("Actual_MarketingCosts["&J$3&"]")="","",INDIRECT("Plan_MarketingCosts["&J$3&"]")-INDIRECT("Actual_MarketingCosts["&J$3&"]")) -> 3000 | ... N26: =IF(INDIRECT("Actual_MarketingCosts["&N$3&"]")="","",INDIRECT("Plan_MarketingCosts["&N$3&"]")-INDIRECT("Actual_MarketingCosts["&N$3&"]")) -> 3500 | O26: =SUM(Var_MarketingCosts[[#This Row],[JANUARY]:[DECEMBER]]) -> -200
B27: Miscellaneous expenses | C27: =IF(INDIRECT("Actual_MarketingCosts["&C$3&"]")="","",INDIRECT("Plan_MarketingCosts["&C$3&"]")-INDIRECT("Actual_MarketingCosts["&C$3&"]")) -> 55 | D27: =IF(INDIRECT("Actual_MarketingCosts["&D$3&"]")="","",INDIRECT("Plan_MarketingCosts["&D$3&"]")-INDIRECT("Actual_MarketingCosts["&D$3&"]")) -> 44 | E27: =IF(INDIRECT("Actual_MarketingCosts["&E$3&"]")="","",INDIRECT("Plan_MarketingCosts["&E$3&"]")-INDIRECT("Actual_MarketingCosts["&E$3&"]")) -> 77 | F27: =IF(INDIRECT("Actual_MarketingCosts["&F$3&"]")="","",INDIRECT("Plan_MarketingCosts["&F$3&"]")-INDIRECT("Actual_MarketingCosts["&F$3&"]")) -> -23 | G27: =IF(INDIRECT("Actual_MarketingCosts["&G$3&"]")="","",INDIRECT("Plan_MarketingCosts["&G$3&"]")-INDIRECT("Actual_MarketingCosts["&G$3&"]")) -> 13 | H27: =IF(INDIRECT("Actual_MarketingCosts["&H$3&"]")="","",INDIRECT("Plan_MarketingCosts["&H$3&"]")-INDIRECT("Actual_MarketingCosts["&H$3&"]")) -> -45 | I27: =IF(INDIRECT("Actual_MarketingCosts["&I$3&"]")="","",INDIRECT("Plan_MarketingCosts["&I$3&"]")-INDIRECT("Actual_MarketingCosts["&I$3&"]")) -> -50 | J27: =IF(INDIRECT("Actual_MarketingCosts["&J$3&"]")="","",INDIRECT("Plan_MarketingCosts["&J$3&"]")-INDIRECT("Actual_MarketingCosts["&J$3&"]")) -> -140 | ... N27: =IF(INDIRECT("Actual_MarketingCosts["&N$3&"]")="","",INDIRECT("Plan_MarketingCosts["&N$3&"]")-INDIRECT("Actual_MarketingCosts["&N$3&"]")) -> 0 | O27: =SUM(Var_MarketingCosts[[#This Row],[JANUARY]:[DECEMBER]]) -> -9
B29: TRAINING / TRAVEL | C29: =SUM(INDIRECT("Var_TrainingTravel["&C$3&"]")) -> 1200 | D29: =SUM(INDIRECT("Var_TrainingTravel["&D$3&"]")) -> -600 | E29: =SUM(INDIRECT("Var_TrainingTravel["&E$3&"]")) -> 1200 | F29: =SUM(INDIRECT("Var_TrainingTravel["&F$3&"]")) -> 1200 | G29: =SUM(INDIRECT("Var_TrainingTravel["&G$3&"]")) -> 2000 | H29: =SUM(INDIRECT("Var_TrainingTravel["&H$3&"]")) -> -2300 | I29: =SUM(INDIRECT("Var_TrainingTravel["&I$3&"]")) -> 500 | J29: =SUM(INDIRECT("Var_TrainingTravel["&J$3&"]")) -> -500 | ... O29: =SUM(INDIRECT("Var_TrainingTravel["&O$3&"]")) -> 2600
B30: TRAINING/TRAVEL | C30: JANUARY | D30: FEBRUARY | E30: MARCH | F30: APRIL | G30: MAY | H30: JUNE | I30: JULY | J30: AUGUST | K30: SEPTEMBER | L30: OCTOBER | M30: NOVEMBER | N30: DECEMBER | O30: TOTAL
B31: Training classes | C31: =IF(INDIRECT("Actual_TrainingTravel["&C$3&"]")="","",INDIRECT("Plan_TrainingTravel["&C$3&"]")-INDIRECT("Actual_TrainingTravel["&C$3&"]")) -> 400 | D31: =IF(INDIRECT("Actual_TrainingTravel["&D$3&"]")="","",INDIRECT("Plan_TrainingTravel["&D$3&"]")-INDIRECT("Actual_TrainingTravel["&D$3&"]")) -> -400 | E31: =IF(INDIRECT("Actual_TrainingTravel["&E$3&"]")="","",INDIRECT("Plan_TrainingTravel["&E$3&"]")-INDIRECT("Actual_TrainingTravel["&E$3&"]")) -> 600 | F31: =IF(INDIRECT("Actual_TrainingTravel["&F$3&"]")="","",INDIRECT("Plan_TrainingTravel["&F$3&"]")-INDIRECT("Actual_TrainingTravel["&F$3&"]")) -> 400 | G31: =IF(INDIRECT("Actual_TrainingTravel["&G$3&"]")="","",INDIRECT("Plan_TrainingTravel["&G$3&"]")-INDIRECT("Actual_TrainingTravel["&G$3&"]")) -> 800 | H31: =IF(INDIRECT("Actual_TrainingTravel["&H$3&"]")="","",INDIRECT("Plan_TrainingTravel["&H$3&"]")-INDIRECT("Actual_TrainingTravel["&H$3&"]")) -> -800 | I31: =IF(INDIRECT("Actual_TrainingTravel["&I$3&"]")="","",INDIRECT("Plan_TrainingTravel["&I$3&"]")-INDIRECT("Actual_TrainingTravel["&I$3&"]")) -> 500 | J31: =IF(INDIRECT("Actual_TrainingTravel["&J$3&"]")="","",INDIRECT("Plan_TrainingTravel["&J$3&"]")-INDIRECT("Actual_TrainingTravel["&J$3&"]")) -> -1000 | ... N31: =IF(INDIRECT("Actual_TrainingTravel["&N$3&"]")="","",INDIRECT("Plan_TrainingTravel["&N$3&"]")-INDIRECT("Actual_TrainingTravel["&N$3&"]")) -> 1800 | O31: =SUM(Var_TrainingTravel[[#This Row],[JANUARY]:[DECEMBER]]) -> 2100
B32: Travel costs | C32: =IF(INDIRECT("Actual_TrainingTravel["&C$3&"]")="","",INDIRECT("Plan_TrainingTravel["&C$3&"]")-INDIRECT("Actual_TrainingTravel["&C$3&"]")) -> 800 | D32: =IF(INDIRECT("Actual_TrainingTravel["&D$3&"]")="","",INDIRECT("Plan_TrainingTravel["&D$3&"]")-INDIRECT("Actual_TrainingTravel["&D$3&"]")) -> -200 | E32: =IF(INDIRECT("Actual_TrainingTravel["&E$3&"]")="","",INDIRECT("Plan_TrainingTravel["&E$3&"]")-INDIRECT("Actual_TrainingTravel["&E$3&"]")) -> 600 | F32: =IF(INDIRECT("Actual_TrainingTravel["&F$3&"]")="","",INDIRECT("Plan_TrainingTravel["&F$3&"]")-INDIRECT("Actual_TrainingTravel["&F$3&"]")) -> 800 | G32: =IF(INDIRECT("Actual_TrainingTravel["&G$3&"]")="","",INDIRECT("Plan_TrainingTravel["&G$3&"]")-INDIRECT("Actual_TrainingTravel["&G$3&"]")) -> 1200 | H32: =IF(INDIRECT("Actual_TrainingTravel["&H$3&"]")="","",INDIRECT("Plan_TrainingTravel["&H$3&"]")-INDIRECT("Actual_TrainingTravel["&H$3&"]")) -> -1500 | I32: =IF(INDIRECT("Actual_TrainingTravel["&I$3&"]")="","",INDIRECT("Plan_TrainingTravel["&I$3&"]")-INDIRECT("Actual_TrainingTravel["&I$3&"]")) -> 0 | J32: =IF(INDIRECT("Actual_TrainingTravel["&J$3&"]")="","",INDIRECT("Plan_TrainingTravel["&J$3&"]")-INDIRECT("Actual_TrainingTravel["&J$3&"]")) -> 500 | ... N32: =IF(INDIRECT("Actual_TrainingTravel["&N$3&"]")="","",INDIRECT("Plan_TrainingTravel["&N$3&"]")-INDIRECT("Actual_TrainingTravel["&N$3&"]")) -> -100 | O32: =SUM(Var_TrainingTravel[[#This Row],[JANUARY]:[DECEMBER]]) -> 500
B34: MONTHLY VARIANCE | C34: =C4+C9+C20+C29 -> 1738 | D34: =D4+D9+D20+D29 -> -984 | E34: =E4+E9+E20+E29 -> 1255 | F34: =F4+F9+F20+F29 -> 301 | G34: =G4+G9+G20+G29 -> 1440 | H34: =H4+H9+H20+H29 -> -3744 | I34: =I4+I9+I20+I29 -> -1875 | J34: =J4+J9+J20+J29 -> 11534 | ... O34: =O4+O9+O20+O29 -> 31458

Sheet Expenses Analysis
B1: EXPENSES ANALYSIS
B2: =" Analysis of data from January to " & PROPER(INDEX('Actual Expenses'!C3:N3,1,MonthsWithActual)) -> Analysis of data from January to December
B4: PLANNED vs ACTUAL EXPENSES | I4: MONTHLY EXPENSES
B11: CATEGORY | C11: PLANNED EXPENSES | D11: ACTUAL EXPENSES | E11: VARIANCE | F11: VARIANCE %
B12: Employee Costs | C12: =SUM(OFFSET('Planned Expenses'!C4,0,0,1,MonthsWithActual)) -> 1355090 | D12: =SUM(OFFSET('Actual Expenses'!C4,0,0,1,MonthsWithActual)) -> 1324150 | E12: =C12-D12 -> 30940 | F12: =E12/C12 -> 0.022832432
B13: Office Costs | C13: =SUM(OFFSET('Planned Expenses'!C9,0,0,1,MonthsWithActual)) -> 138740 | D13: =SUM(OFFSET('Actual Expenses'!C9,0,0,1,MonthsWithActual)) -> 139583 | E13: =C13-D13 -> -843 | F13: =E13/C13 -> -0.0060761136
B14: Marketing Costs | C14: =SUM(OFFSET('Planned Expenses'!C20,0,0,1,MonthsWithActual)) -> 67800 | D14: =SUM(OFFSET('Actual Expenses'!C20,0,0,1,MonthsWithActual)) -> 69039 | E14: =C14-D14 -> -1239 | F14: =E14/C14 -> -0.018274336
B15: Training / Travel | C15: =SUM(OFFSET('Planned Expenses'!C29,0,0,1,MonthsWithActual)) -> 48000 | D15: =SUM(OFFSET('Actual Expenses'!C29,0,0,1,MonthsWithActual)) -> 45400 | E15: =C15-D15 -> 2600 | F15: =E15/C15 -> 0.054166667
P16: s
